nion/ipython_kernel/__init__.py
nion/ipython_kernel/heartbeat.py
nion/ipython_kernel/ipython_kernel.py
nion/ipython_kernel/magic.py
nion/ipython_kernel/mpl_backend_inline.py
nion/ipython_kernel/mpl_backend_swift.py
nion/ipython_kernel/paths.py
nion/ipython_kernel/py.typed
nion/ipython_kernel/zmqstream.py
nionswift_plugin/ipython_kernel_extension/__init__.py
nionswift_plugin/ipython_kernel_extension/kernel_extension.py
nionswift_plugin/ipython_kernel_extension/py.typed
nionswift_ipython_kernel-0.1.1.dist-info/METADATA
nionswift_ipython_kernel-0.1.1.dist-info/WHEEL
nionswift_ipython_kernel-0.1.1.dist-info/top_level.txt
nionswift_ipython_kernel-0.1.1.dist-info/RECORD
