Metadata-Version: 2.4
Name: nionswift-ipython-kernel
Version: 0.1.1
Summary: An iPython kernel for Nion Swift.
Author-email: Nion Software <swift@nion.com>
License-Expression: Apache-2.0
Project-URL: Homepage, https://github.com/nion-software/nionswift-ipython-kernel
Classifier: Development Status :: 4 - Beta
Classifier: Intended Audience :: Developers
Classifier: Programming Language :: Python :: 3.12
Classifier: Programming Language :: Python :: 3.13
Requires-Python: >=3.12
